need_an_image/__init__.py
need_an_image/engines/__init__.py
need_an_image/engines/bing.py
need_an_image/utils/__init__.py
need_an_image/utils/decorators.py
need_an_image/utils/store.py
i_need_an_image-0.3.4.dist-info/LICENSE
i_need_an_image-0.3.4.dist-info/METADATA
i_need_an_image-0.3.4.dist-info/WHEEL
i_need_an_image-0.3.4.dist-info/top_level.txt
i_need_an_image-0.3.4.dist-info/RECORD
