Metadata-Version: 2.1
Name: i-need-an-image
Version: 0.3.4
Summary: Download only one image from web
Home-page: https://github.com/RyouMon/i-need-an-image
Author: Wen Liang
Author-email: wenslife@outlook.com
License: UNKNOWN
Project-URL: Bug Tracker, https://github.com/RyouMon/i-need-an-image/issues
Platform: UNKNOWN
Classifier: Programming Language :: Python :: 3
Classifier: License :: OSI Approved :: MIT License
Classifier: Operating System :: OS Independent
Requires-Python: >=3.6
License-File: LICENSE
Requires-Dist: Pillow (>=8.0)
Requires-Dist: requests (>=2.0)
Requires-Dist: beautifulsoup4 (==4.9.3)
Requires-Dist: lxml (==4.7.1)
Requires-Dist: jieba (>=0.42.1)
